[
    {
        "id": 1,
        "img": "../images/la-vaca-se-empaca.png",
        "titulo": "LA VACA SE EMPACA",
        "autor": "Lynch Agustina",
        "fechaPublicacion": "Octubre 2020",
        "editorial": "Edición Autor",
        "formato": "Tapa dura",
        "idioma": "Español",
        "cantidadPaginas": 38,
        "isbn": "9789878661735",
        "rangoEdad": "2 - 4 años",
        "sipnosis": "Cada vez que la vaca Paca tiene un berrinche, sus padres, en vez de ayudar, no saben cómo actuar. Así que Paca va a recorrer la granja para pedirles consejos a sus amigos, y así darles ideas a sus padres sobre cómo reaccionar.\nContado para niños, pero pensado para grandes, este cuento nos da consejos sobre cómo podemos actuar cuando nuestros hijos tienen berrinches.",
        "stockLibro": 8,
        "precio": 2800
    },

    {
        "id": 2,
        "img": "../images/caillou-es-mio.png",
        "titulo": "CAILLOU ¡ES MÍO!",
        "autor": "Sanschagrin Joceline ",
        "fechaPublicacion": "Agosto 2018",
        "editorial": "La Brujita de Papel",
        "formato": "Tapa dura",
        "idioma": "Español",
        "cantidadPaginas": 22,
        "isbn": "9789873681905",
        "rangoEdad": "2 - 4 años",
        "sipnosis": "Caillou está creciendo y su mundo se agranda. Paso a paso él va ganando mayor independencia.A veces es difícil compartir lo que es de uno. Al final, Caillou y su amigo deciden intercambiar sus juguetes.",
        "stockLibro": 10,
        "precio": 1700
    },

    {
        "id": 3,
        "img": "../images/las-emociones-animagenes.png",
        "titulo": "LAS EMOCIONES - MIS ANIMÁGENES",
        "autor": "Editores de Auzou",
        "fechaPublicacion": "Mayo 2020",
        "editorial": "Auzou",
        "formato": "Tapa dura",
        "idioma": "Español",
        "cantidadPaginas": 10,
        "isbn": "9782733895900",
        "rangoEdad": "0 - 2 años",
        "sipnosis": "Descubre las distintas emociones gracias a mecanismos simples y fáciles de activar.\nEn la última página, diviértete adivinando lo que se esconde bajo las solapas.",
        "stockLibro": 4,
        "precio": 3990
    },
    {
        "id": 4,
        "img": "../images/atrapala-kitty.png",
        "titulo": "ATRÁPALA KITTY",
        "autor": "Parsons Nicola ",
        "fechaPublicacion": "Julio 2019",
        "editorial": "Manolito Books",
        "formato": "Tapa dura",
        "idioma": "Español",
        "cantidadPaginas": 24,
        "isbn": "9788417299453",
        "rangoEdad": "2 - 4 años",
        "sipnosis": "Kitty ama jugar con su suave bola de estambre. Tanto, que no quiere compartirla con nadie, pero pronto aprenderá que jugar sola no es tan divertido.\n¿Entenderá Kitty la magia de compartir? Descúbrelo en esta tierna historia con Puppy, Rabbit y todos los amigos de Kitty.",
        "stockLibro": 20,
        "precio": 1800
    },

    {
        "id": 5,
        "img": "../images/muevo-miro-selva.png",
        "titulo": "MUEVO Y MIRO - EN LA SELVA",
        "autor": "Editores de Yoyo Books",
        "fechaPublicacion": "Octubre 2020",
        "editorial": "Yoyo Books",
        "formato": "Tapa dura",
        "idioma": "Español",
        "cantidadPaginas": 10,
        "isbn": "9789463993500",
        "rangoEdad": "2 - 4 años",
        "sipnosis": "¡Visita a los animales que viven en la selva!\n¡Mueve las lengüetas y te sorprenderás!\nEscenas alegres que fascinarán a los pequeños y estimularán su motricidad.",
        "stockLibro": 5,
        "precio": 3490
    },

    {
        "id": 6,
        "img": "../images/primer-dia-clases.png",
        "titulo": "PRIMER DÍA DE CLASES",
        "autor": "Sin Autor",
        "fechaPublicacion": "",
        "editorial": "Grupo Sin Fronteras",
        "formato": "Tapa dura",
        "idioma": "Español",
        "cantidadPaginas": 10,
        "isbn": "9789585541085",
        "rangoEdad": "0 - 2 años",
        "sipnosis": "¡Libros perfectos para manos pequeñas! El innovador formato de rueda giratoria brinda una forma divertida para que los más pequeños aprendan los números hasta el 5 y también mejoren las habilidades de motricidad fina. Entretenimiento y risas con personajes coloridos.",
        "stockLibro": 4,
        "precio": 3790
    },

    {
        "id": 7,
        "img": "../images/conviertete-heroe-ines-pricesita.png",
        "titulo": "CONVIÉRTETE EN HÉROE CON INÉS LA PRINCESITA",
        "autor": "Editores de Auzou",
        "fechaPublicacion": "Agosto 2018",
        "editorial": "Auzou",
        "formato": "Tapa dura",
        "idioma": "Español",
        "cantidadPaginas": 20,
        "isbn": "9782733866771",
        "rangoEdad": "2 - 4 años",
        "sipnosis": "¡Inés debe encontrar un regalo para su madre, la reina!\nPero se presentan ante ella diferentes posibilidades: ¡y te necesita a ti! A lo largo de la historia, tus elecciones la conducirán a vivir aventuras muy diferentes.\nConviértete en héroe y elige en cada página una pestaña para continuar la historia",
        "stockLibro": 11,
        "precio": 3290
    },

    {
        "id": 8,
        "img": "../images/libro-gigante-animales.png",
        "titulo": "MI LIBRO GIGANTE DE ANIMALES",
        "autor": "Editores de Auzou",
        "fechaPublicacion": "Octubre 2018",
        "editorial": "Auzou",
        "formato": "Tapa dura",
        "idioma": "Español",
        "cantidadPaginas": 8,
        "isbn": "9782733884782",
        "rangoEdad": "0 - 2 años",
        "sipnosis": "Este libro GIGANTE llamará la atención de los más pequeños. En cada página les esperan tres texturas para tocar; un espejo; una solapa de tela y un montón de sorpresas para explorar este universo en cuatro patas.",
        "stockLibro": 2,
        "precio": 9990
    },

    {
        "id": 9,
        "img": "../images/la-selva-sabana-animagenes.png",
        "titulo": "LA SELVA Y LA SABANA - MIS ANIMÁGENES",
        "autor": "Editores de Auzou",
        "fechaPublicacion": "Septiembre 2018",
        "editorial": "Auzou",
        "formato": "Tapa dura",
        "idioma": "Español",
        "cantidadPaginas": 10,
        "isbn": "9782733885505",
        "rangoEdad": "0 - 2 años",
        "sipnosis": "Descubre los animales de la selva y de la sabana gracias a mecanismos divertidos y fáciles de activar.\nEn la última página, diviértete adivinando lo que se esconde bajo las solapas.",
        "stockLibro": 6,
        "precio": 3990
    },

    {
        "id": 10,
        "img": "../images/la-vaca-y-la-espinaca.png",
        "titulo": "LA VACA Y LA ESPINACA",
        "autor": "Lynch Agustina",
        "fechaPublicacion": "Julio 2019",
        "editorial": "Editorial el Ateneo",
        "formato": "Tapa dura",
        "idioma": "Español",
        "cantidadPaginas": 36,
        "isbn": "9789500210041",
        "rangoEdad": "0 - 2 años",
        "sipnosis": "La vaca Paca no se anima a probar nuevas comidas. Solo quiere comer fideos. Pero Mamá Vaca y el resto de los amigos de la granja la ayudarán a comer mejor.\nEscrito con rimas y con los simpáticos sonidos de los animalitos de la granja, este libro nos invita a leerles a los chicos un cuento como a ellos les gusta: con ruidos, colores y risas. Y así, sutilmente, podemos ayudarlos a que prueben nuevos sabores.",
        "stockLibro": 15,
        "precio": 2700
    },

    {
        "id": 11,
        "img": "../images/caillou-no-mas-panales.png",
        "titulo": "CAILLOU NO MAS PAÑALES",
        "autor": "L'Heureux Christine",
        "fechaPublicacion": "Agosto 2011",
        "editorial": "La Brujita de Papel",
        "formato": "Tapa dura",
        "idioma": "Español",
        "cantidadPaginas": 22,
        "isbn": "9789874918864",
        "rangoEdad": "2 - 4 años",
        "sipnosis": "Caillou ya sabe cuándo usar la pelela. ¡Por eso ahora él quiere usar el inodoro de grandes y dejar de usar pañales de noche!",
        "stockLibro": 2,
        "precio": 1650
    },

    {
        "id": 12,
        "img": "../images/a-la-cama-animagenes.png",
        "titulo": "¡A LA CAMA! - MIS ANIMÁGENES",
        "autor": "Editores de Auzou",
        "fechaPublicacion": "Marzo 2017",
        "editorial": "Auzou",
        "formato": "Tapa dura",
        "idioma": "Español",
        "cantidadPaginas": 10,
        "isbn": "9782733857748",
        "rangoEdad": "0 - 2 años",
        "sipnosis": "Descubre las diferentes etapas de la hora de ir a la cama gracias a mecanismos divertidos y fáciles de activar.\nEn la última página, diviértete adivinando lo que se esconde bajo las solapas.",
        "stockLibro": 4,
        "precio": 3990
    },

    {
        "id": 13,
        "img": "../images/cuentos-montessori-crecer-felices.png",
        "titulo": "CUENTOS MONTESSORI PARA CRECER FELICES",
        "autor": "Prada Marta",
        "fechaPublicacion": "Octubre 2018",
        "editorial": "Nube de Tinta",
        "formato": "Rústica",
        "idioma": "Español",
        "cantidadPaginas": 96,
        "isbn": "9789871997589",
        "rangoEdad": "4 - 6 años",
        "sipnosis": "Como familia, la crianza nos presenta nuevos retos cada día: el sueño, el pañal, la llegada de un nuevo hermano, las frustraciones, los miedos... ¿Qué mejor manera de afrontarlos que desde el respeto, la empatía y la consciencia? Con cuentos para los niños y explicaciones para los padres, este precioso libro de la autora del conocido blog Pequefelicidad los ayudará a crecer juntos a partir de los principios de la filosofía Montessori y la crianza respetuosa.",
        "stockLibro": 12,
        "precio": 3500
    },

    {
        "id": 14,
        "img": "../images/cuentos-montessori-buenas-noches.png",
        "titulo": "CUENTOS MONTESSORI PARA LAS BUENAS NOCHES",
        "autor": "Prada Marta",
        "fechaPublicacion": "Octubre 2019",
        "editorial": "Nube de Tinta",
        "formato": "Rústica",
        "idioma": "Español",
        "cantidadPaginas": 96,
        "isbn": "9788417605148",
        "rangoEdad": "4 - 6 años",
        "sipnosis": "Nuestros pequeños crecen cada día, y es importante guardar un momento antes de acostarse para parar, conectar y empatizar con ellos, compartir vivencias y expresar emociones que necesitan de ese momento de reposo para salir. El sueño es fundamental en su desarrollo y el momento justo de antes de ir a dormir influye en su calidad y en los pensamientos y emociones que quedan en el cerebro justo antes de entrar en este modo de «desconexión y procesamiento de información».\nEste libro se convertirá en la herramienta de papel ideal para encontrar vuestro momento al final del día para miraros a los ojos, inspirar calma, naturaleza, valorar lo cotidiano, apreciar el mundo en todos sus aspectos y alentar a los niños y niñas a ser ellos mismos\n«Siembra en los niños ideas buenas aunque no las entiendan.Los años se encargarán de descifrarlas en su entendimiento y de hacerlas crecer en su corazón.» María Montessori",
        "stockLibro": 8,
        "precio": 3500
    }
]